{
	"publisher": "twitter",
	"streamType": "track",
	"dataFormat": "original",
	"fromDate": "201205020000",
	"toDate": "201205032359",
	"rules": [
		{"value":"@davidpujadas"},
		{"value":"@LeMondefr"},
		{"value":"@lemonde_pol"},
		{"value":"@Le_Figaro"},
		{"value":"@LaurenceFerrari"},
		{"value":"@FrancoisFillon"},
		{"value":"@jeanmarcayrault"},
		{"value":"@fhollande"},
		{"value":"@nicolassarkozy"},
		{"value":"@Arthaud2012"},
		{"value":"@JLMelenchon"},
		{"value":"@bayrou"},
		{"value":"@JCheminade"},
		{"value":"@dupontaignan"},
		{"value":"@EvaJoly"},
		{"value":"@MLP_officiel"},
		{"value":"@PhillipePoutou"},
		{"value":"@partisocialiste"},
		{"value":"@UMP"},
		{"value":"@jeunesump"},
		{"value":"@LutteOuvrier"},
		{"value":"@partisocialiste"},
		{"value":"@LePG"},
		{"value":"@MoDem"},
		{"value":"@SetP_officiel"},
		{"value":"@EELV"},
		{"value":"@FN2012"},
		{"value":"@FN_officiel"},
		{"value":"@NPA200"}
	],
	"title":"france_debate_users_top_mentions",
	"serviceUsername": "dvshah"
}