	{
	"publisher": "twitter",
	"streamType": "track",
	"dataFormat": "original",
	"fromDate": "201305110000",
	"toDate": "201305202359",
	"rules": [

{"value":"contains:\"supreme court ruling\""},
{"value":"contains:scotus"},
{"value":"contains:Monsanto"},
{"value":"contains:\"Monsanto's patent\""},
{"value":"contains:\"seed replication\""},
{"value":"contains:\"self replication\""},
{"value":"contains:soybeans"},
{"value":"contains:patent"},
{"value":"contains:\"seed patent\""},
{"value":"contains:antitrust"},
{"value":"contains:\"exhaustion doctrine\""},
{"value":"contains:\"patent exhaustion\""},
{"value":"contains:\"patent law\""},
{"value":"contains:\"patented soybeans\""},
{"value":"contains:\"patent licensing\""},
{"value":"contains:biotech"},
{"value":"contains:biofuel"},
{"value":"contains:Bowman"},
{"value":"contains:\"Bowman v. Monsanto\""},
{"value":"contains:\"Vermon Bowman\""},
{"value":"contains:GMO"},
{"value":"contains:\"non genetically modified\""},
{"value":"contains:\"genetically altered\""},
{"value":"contains:\"genetically engineered\""},
{"value":"contains:\"genetically modified seed\""},
{"value":"contains:\"gm seed\""},
{"value":"contains:\"genetically modified crops\""},
{"value":"contains:\"genetically modified food\""},
{"value":"contains:corn"},
{"value":"contains:\"GMO crops\""},
{"value":"contains:\"GMO seed\""},
{"value":"contains:Roundup"},
{"value":"contains:\"roundup ready\""},
{"value":"contains:\"Roundup ready seeds\""},
{"value":"contains:glyphosate"},
{"value":"contains:glyphosate-resistant"},
{"value":"#stopmonsanto"},
{"value":"#marchagainstmonsanto"},
{"value":"#labelgmos"},
{"value":"#monsanto"},
{"value":"#mam"},
{"value":"#gmo"},
{"value":"#gmos"},
{"value":"#nogmo"},
{"value":"#farmbill"},
{"value":"#scotus"},
{"value":"#m25"},
{"value":"#25m"},
{"value":"#antitrust"},
{"value":"#patent"},
{"value":"#roundup"},
{"value":"#biofuels"}

	],
	"title":"sc_monsanto_terms_top_contains",
	"serviceUsername": "dvshah"
}